ape_starknet/__init__.py
ape_starknet/_cli.py
ape_starknet/config.py
ape_starknet/conversion.py
ape_starknet/ecosystems.py
ape_starknet/exceptions.py
ape_starknet/explorer.py
ape_starknet/provider.py
ape_starknet/py.typed
ape_starknet/tokens.py
ape_starknet/transactions.py
ape_starknet/types.py
ape_starknet/udc.py
ape_starknet/version.py
ape_starknet/accounts/__init__.py
ape_starknet/accounts/_cli.py
ape_starknet/utils/__init__.py
ape_starknet/utils/basemodel.py
ape_starknet-0.6.0.dist-info/LICENSE
ape_starknet-0.6.0.dist-info/METADATA
ape_starknet-0.6.0.dist-info/WHEEL
ape_starknet-0.6.0.dist-info/entry_points.txt
ape_starknet-0.6.0.dist-info/top_level.txt
ape_starknet-0.6.0.dist-info/RECORD
